{
  "products": [
    {
      "id": 1,
      "name": "iPhone 15 Pro",
      "desc": "Apple iPhone 13th generation",
      "price": 1449,
      "color": "#33505a",
      "image": "https://pngimg.com/uploads/iphone_12/small/iphone_12_PNG31.png"
    },
    {
      "id": 2,
      "name": "Galaxy Z-Flip",
      "desc": "Samsung Galaxy Z Flip Phone",
      "price": 699,
      "color": "#00ac51",
      "image": "https://upload.wikimedia.org/wikipedia/commons/thumb/d/dd/Galaxy_Z_Flip.png/1200px-Galaxy_Z_Flip.png"
    },
    {
      "id": 3,
      "name": "M1 Macbook Air",
      "desc": "Apple Macbook air with apple silicon",
      "price": 1099,
      "color": "#e0bfae",
      "image": "https://pngimg.com/uploads/macbook/small/macbook_PNG101753.png"
    },
    {
      "id": 4,
      "name": "Playstation 5",
      "desc": "Sony Playstation 5th generation",
      "price": 500,
      "color": "#544ee4",
      "image": "https://www.pngall.com/wp-content/uploads/14/PS5-Transparent.png"
    },
    {
      "id": 5,
      "name": "Airpods Pro",
      "desc": "Apple Aipods Pro 1st generation",
      "price": 200,
      "color": "#e3e4e9",
      "image": "https://parspng.com/wp-content/uploads/2023/08/airpodspng.parspng.com-4-600x600.png"
    },
    {
      "id": 6,
      "name": "iPad Pro",
      "desc": "Apple iPad Pro 2020 edition",
      "price": 799,
      "color": "#f73984",
      "image": "https://www.pngarts.com/files/5/IPad-Free-PNG-Image.png"
    },
    {
      "id": 7,
      "name": "Legion 9i",
      "desc": "Legion 9i Gen 10 (18″ Intel)",
      "price": 1299,
      "color": "#1c1c1c",
      "image": "https://p2-ofp.static.pub/ShareResource/ww/landing-pages/legion-brand-2025/Agnostic-version/img/lenovo-legion-91-gen-10-front-back-img.png"
    },
    {
      "id": 8,
      "name": "Lenovo Legion Go",
      "desc": "Lenovo Legion Go Gen 2 (8.8″)",
      "price": 899,
      "color": "#7c95eb",
      "image": "https://p4-ofp.static.pub/ShareResource/ww/landing-pages/legion-brand-2025/Agnostic-version/img/lenovo-legion-go-gen-2-img.png"
    }
  ]
}
